sk_sugar/__init__.py
sk_sugar/_nbdev.py
sk_sugar/core.py
sk_sugar-0.0.6.dist-info/LICENSE
sk_sugar-0.0.6.dist-info/METADATA
sk_sugar-0.0.6.dist-info/WHEEL
sk_sugar-0.0.6.dist-info/top_level.txt
sk_sugar-0.0.6.dist-info/RECORD
